plone.app.imaging-2.1.1-py2.7-nspkg.pth
plone/app/imaging/__init__.py
plone/app/imaging/configure.zcml
plone/app/imaging/interfaces.py
plone/app/imaging/monkey.py
plone/app/imaging/scale.py
plone/app/imaging/scaling.py
plone/app/imaging/testing.py
plone/app/imaging/testing.zcml
plone/app/imaging/traverse.py
plone/app/imaging/utils.py
plone/app/imaging/tests/__init__.py
plone/app/imaging/tests/base.py
plone/app/imaging/tests/image.gif
plone/app/imaging/tests/image.jpg
plone/app/imaging/tests/image.png
plone/app/imaging/tests/test_doctests.py
plone/app/imaging/tests/test_new_scaling.py
plone/app/imaging/tests/test_properties.py
plone/app/imaging/tests/test_scaling.py
plone/app/imaging/tests/test_setup.py
plone/app/imaging/tests/test_traverse.py
plone/app/imaging/tests/transforms.txt
plone/app/imaging/tests/traversal.txt
plone/app/imaging/tests/utils.py
plone.app.imaging-2.1.1.dist-info/METADATA
plone.app.imaging-2.1.1.dist-info/WHEEL
plone.app.imaging-2.1.1.dist-info/entry_points.txt
plone.app.imaging-2.1.1.dist-info/namespace_packages.txt
plone.app.imaging-2.1.1.dist-info/top_level.txt
plone.app.imaging-2.1.1.dist-info/RECORD
