Metadata-Version: 2.1
Name: plone.app.imaging
Version: 2.1.1
Summary: User-configurable, blob-aware image scaling for Plone.
Home-page: https://github.com/plone/plone.app.imaging
Author: Plone Foundation
Author-email: plone-developers@lists.sourceforge.net
License: GPL version 2
Keywords: images scaling zodb blob plone
Platform: Any
Classifier: Development Status :: 5 - Production/Stable
Classifier: Environment :: Web Environment
Classifier: Framework :: Plone
Classifier: Framework :: Plone :: 5.0
Classifier: Framework :: Plone :: 5.1
Classifier: Framework :: Plone :: 5.2
Classifier: Framework :: Zope2
Classifier: Framework :: Zope :: 4
Classifier: Intended Audience :: Developers
Classifier: Intended Audience :: Other Audience
Classifier: Intended Audience :: System Administrators
Classifier: License :: OSI Approved :: GNU General Public License v2 (GPLv2)
Classifier: Operating System :: OS Independent
Classifier: Programming Language :: Python
Classifier: Programming Language :: Python :: 2.7
Requires-Dist: setuptools
Requires-Dist: plone.scale[storage]
Requires-Dist: Products.Archetypes
Requires-Dist: z3c.caching
Requires-Dist: five.globalrequest
Provides-Extra: test
Requires-Dist: plone.app.testing ; extra == 'test'
Requires-Dist: Products.ATContentTypes ; extra == 'test'
